musct/__init__.py
musct/args.py
musct/cli_command.py
musct/cmd_backup.py
musct/cmd_check.py
musct/cmd_install.py
musct/cmd_list.py
musct/fileutils.py
musct/log.py
musct/main.py
musct/package.py
musct/printer.py
musct/reference.py
musct/root.py
musct/settings.py
musct/template.py
musct/yaml_wrapper.py
musct/templates/__init__.py
musct/templates/tpl_copy.py
musct/templates/tpl_executable_file.py
musct/templates/tpl_home_dir.py
musct/templates/tpl_home_file.py
musct/templates/tpl_icons_dir.py
musct/templates/tpl_systemd_service_file.py
musct/templates/tpl_themes_dir.py
musct/templates/tpl_xdg_cfg_dir.py
musct/templates/tpl_xdg_cfg_file.py
musct-1.0.1.dist-info/METADATA
musct-1.0.1.dist-info/RECORD
musct-1.0.1.dist-info/WHEEL
musct-1.0.1.dist-info/entry_points.txt
musct-1.0.1.dist-info/top_level.txt
