Metadata-Version: 2.1
Name: musct
Version: 1.0.1
Summary: Multiple user setting configuration tool
Home-page: https://gitlab.com/xythrez/musct
Author: Yiyao Yu
Author-email: yuydevel@protonmail.com
License: UNKNOWN
Keywords: rice settings config helper
Platform: UNKNOWN
Classifier: Operating System :: POSIX :: BSD
Classifier: Operating System :: POSIX :: Linux
Classifier: Programming Language :: Python :: 3.6
Classifier: License :: OSI Approved :: GNU General Public License v3 (GPLv3)
Classifier: Development Status :: 4 - Beta
Classifier: Intended Audience :: Developers
Requires-Dist: pyyaml
